{"pesos_meta_dict": {"Discos de Corte": [0.45, 225], "Lixas": [0.25, 125], "Discos Diamantados": [0.1, 50], "Rebolos": [0.08, 40], "Discos de Fibra": [0.05, 25], "Super Abrasivos": [0.03, 15], "Flap Discs": [0.02, 10], "Mantas NW": [0.01, 5], "Fitas": [0.01, 5]}, "linhas_aceleradoras": ["Discos de Corte", "Discos de Fibra"], "baralho_dict": {"31": {"Dia": {"5-1": 5, "5-2": 5, "5-3": 5, "5-4": 5, "10-1": 10, "10-2": 10, "10-3": 10, "10-4": 10, "15-1": 15, "15-2": 15, "15-3": 15, "15-4": 15, "20-1": 20, "20-2": 20, "20-3": 20, "20-4": 20, "25-1": 25, "25-2": 25, "25-3": 25, "25-4": 25, "30-1": 30, "30-2": 30, "30-3": 30, "30-4": 30}, "Carta": {"5-1": 1, "5-2": 2, "5-3": 3, "5-4": 4, "10-1": 1, "10-2": 2, "10-3": 3, "10-4": 4, "15-1": 1, "15-2": 2, "15-3": 3, "15-4": 4, "20-1": 1, "20-2": 2, "20-3": 3, "20-4": 4, "25-1": 1, "25-2": 2, "25-3": 3, "25-4": 4, "30-1": 1, "30-2": 2, "30-3": 3, "30-4": 4}, "Linha": {"5-1": "Lixas", "5-2": "Super Abrasivos", "5-3": "Fitas", "5-4": "Flap Discs", "10-1": "Discos de Corte", "10-2": "Super Abrasivos", "10-3": "Mantas NW", "10-4": "Fitas", "15-1": "Lixas", "15-2": "Rebolos", "15-3": "Mantas NW", "15-4": "Super Abrasivos", "20-1": "Discos de Corte", "20-2": "Mantas NW", "20-3": "Rebolos", "20-4": "Super Abrasivos", "25-1": "Discos de Corte", "25-2": "Super Abrasivos", "25-3": "Mantas NW", "25-4": "Discos de Fibra", "30-1": "Discos de Corte", "30-2": "Mantas NW", "30-3": "Fitas", "30-4": "Rebolos"}, "Valor": {"5-1": 40, "5-2": 30, "5-3": 10, "5-4": 40, "10-1": 100, "10-2": 50, "10-3": 30, "10-4": 20, "15-1": 100, "15-2": 40, "15-3": 10, "15-4": 20, "20-1": 80, "20-2": 10, "20-3": 40, "20-4": 30, "25-1": 100, "25-2": 40, "25-3": 20, "25-4": 20, "30-1": 50, "30-2": 40, "30-3": 30, "30-4": 50}, "Acelerador": {"5-1": false, "5-2": false, "5-3": false, "5-4": false, "10-1": true, "10-2": false, "10-3": false, "10-4": false, "15-1": false, "15-2": false, "15-3": false, "15-4": false, "20-1": true, "20-2": false, "20-3": false, "20-4": false, "25-1": true, "25-2": false, "25-3": false, "25-4": true, "30-1": true, "30-2": false, "30-3": false, "30-4": false}}, "42": {"Dia": {"5-1": 5, "5-2": 5, "5-3": 5, "5-4": 5, "10-1": 10, "10-2": 10, "10-3": 10, "10-4": 10, "15-1": 15, "15-2": 15, "15-3": 15, "15-4": 15, "20-1": 20, "20-2": 20, "20-3": 20, "20-4": 20, "25-1": 25, "25-2": 25, "25-3": 25, "25-4": 25, "30-1": 30, "30-2": 30, "30-3": 30, "30-4": 30}, "Carta": {"5-1": 1, "5-2": 2, "5-3": 3, "5-4": 4, "10-1": 1, "10-2": 2, "10-3": 3, "10-4": 4, "15-1": 1, "15-2": 2, "15-3": 3, "15-4": 4, "20-1": 1, "20-2": 2, "20-3": 3, "20-4": 4, "25-1": 1, "25-2": 2, "25-3": 3, "25-4": 4, "30-1": 1, "30-2": 2, "30-3": 3, "30-4": 4}, "Linha": {"5-1": "Discos de Corte", "5-2": "Discos de Fibra", "5-3": "Super Abrasivos", "5-4": "Rebolos", "10-1": "Lixas", "10-2": "Super Abrasivos", "10-3": "Fitas", "10-4": "Flap Discs", "15-1": "Lixas", "15-2": "Flap Discs", "15-3": "Fitas", "15-4": "Super Abrasivos", "20-1": "Lixas", "20-2": "Discos de Fibra", "20-3": "Rebolos", "20-4": "Super Abrasivos", "25-1": "Discos de Corte", "25-2": "Flap Discs", "25-3": "Rebolos", "25-4": "Mantas NW", "30-1": "Lixas", "30-2": "Fitas", "30-3": "Flap Discs", "30-4": "Rebolos"}, "Valor": {"5-1": 80, "5-2": 50, "5-3": 30, "5-4": 40, "10-1": 40, "10-2": 50, "10-3": 50, "10-4": 10, "15-1": 100, "15-2": 30, "15-3": 10, "15-4": 10, "20-1": 100, "20-2": 40, "20-3": 30, "20-4": 40, "25-1": 80, "25-2": 30, "25-3": 10, "25-4": 30, "30-1": 80, "30-2": 30, "30-3": 10, "30-4": 50}, "Acelerador": {"5-1": true, "5-2": true, "5-3": false, "5-4": false, "10-1": false, "10-2": false, "10-3": false, "10-4": false, "15-1": false, "15-2": false, "15-3": false, "15-4": false, "20-1": false, "20-2": true, "20-3": false, "20-4": false, "25-1": true, "25-2": false, "25-3": false, "25-4": false, "30-1": false, "30-2": false, "30-3": false, "30-4": false}}, "51": {"Dia": {"5-1": 5, "5-2": 5, "5-3": 5, "5-4": 5, "10-1": 10, "10-2": 10, "10-3": 10, "10-4": 10, "15-1": 15, "15-2": 15, "15-3": 15, "15-4": 15, "20-1": 20, "20-2": 20, "20-3": 20, "20-4": 20, "25-1": 25, "25-2": 25, "25-3": 25, "25-4": 25, "30-1": 30, "30-2": 30, "30-3": 30, "30-4": 30}, "Carta": {"5-1": 1, "5-2": 2, "5-3": 3, "5-4": 4, "10-1": 1, "10-2": 2, "10-3": 3, "10-4": 4, "15-1": 1, "15-2": 2, "15-3": 3, "15-4": 4, "20-1": 1, "20-2": 2, "20-3": 3, "20-4": 4, "25-1": 1, "25-2": 2, "25-3": 3, "25-4": 4, "30-1": 1, "30-2": 2, "30-3": 3, "30-4": 4}, "Linha": {"5-1": "Lixas", "5-2": "Mantas NW", "5-3": "Fitas", "5-4": "Rebolos", "10-1": "Discos de Corte", "10-2": "Super Abrasivos", "10-3": "Mantas NW", "10-4": "Flap Discs", "15-1": "Discos de Corte", "15-2": "Mantas NW", "15-3": "Discos de Fibra", "15-4": "Rebolos", "20-1": "Discos Diamantados", "20-2": "Rebolos", "20-3": "Mantas NW", "20-4": "Discos de Fibra", "25-1": "Discos de Corte", "25-2": "Discos de Fibra", "25-3": "Flap Discs", "25-4": "Super Abrasivos", "30-1": "Lixas", "30-2": "Rebolos", "30-3": "Discos de Fibra", "30-4": "Mantas NW"}, "Valor": {"5-1": 80, "5-2": 20, "5-3": 20, "5-4": 30, "10-1": 100, "10-2": 20, "10-3": 10, "10-4": 10, "15-1": 40, "15-2": 40, "15-3": 10, "15-4": 20, "20-1": 40, "20-2": 40, "20-3": 50, "20-4": 10, "25-1": 80, "25-2": 20, "25-3": 50, "25-4": 50, "30-1": 100, "30-2": 40, "30-3": 20, "30-4": 50}, "Acelerador": {"5-1": false, "5-2": false, "5-3": false, "5-4": false, "10-1": true, "10-2": false, "10-3": false, "10-4": false, "15-1": true, "15-2": false, "15-3": true, "15-4": false, "20-1": false, "20-2": false, "20-3": false, "20-4": true, "25-1": true, "25-2": true, "25-3": false, "25-4": false, "30-1": false, "30-2": false, "30-3": true, "30-4": false}}, "73": {"Dia": {"5-1": 5, "5-2": 5, "5-3": 5, "5-4": 5, "10-1": 10, "10-2": 10, "10-3": 10, "10-4": 10, "15-1": 15, "15-2": 15, "15-3": 15, "15-4": 15, "20-1": 20, "20-2": 20, "20-3": 20, "20-4": 20, "25-1": 25, "25-2": 25, "25-3": 25, "25-4": 25, "30-1": 30, "30-2": 30, "30-3": 30, "30-4": 30}, "Carta": {"5-1": 1, "5-2": 2, "5-3": 3, "5-4": 4, "10-1": 1, "10-2": 2, "10-3": 3, "10-4": 4, "15-1": 1, "15-2": 2, "15-3": 3, "15-4": 4, "20-1": 1, "20-2": 2, "20-3": 3, "20-4": 4, "25-1": 1, "25-2": 2, "25-3": 3, "25-4": 4, "30-1": 1, "30-2": 2, "30-3": 3, "30-4": 4}, "Linha": {"5-1": "Lixas", "5-2": "Flap Discs", "5-3": "Rebolos", "5-4": "Super Abrasivos", "10-1": "Discos de Corte", "10-2": "Mantas NW", "10-3": "Discos de Fibra", "10-4": "Flap Discs", "15-1": "Discos Diamantados", "15-2": "Mantas NW", "15-3": "Flap Discs", "15-4": "Fitas", "20-1": "Lixas", "20-2": "Rebolos", "20-3": "Mantas NW", "20-4": "Flap Discs", "25-1": "Lixas", "25-2": "Super Abrasivos", "25-3": "Discos de Fibra", "25-4": "Rebolos", "30-1": "Discos de Corte", "30-2": "Rebolos", "30-3": "Flap Discs", "30-4": "Fitas"}, "Valor": {"5-1": 100, "5-2": 40, "5-3": 20, "5-4": 10, "10-1": 80, "10-2": 30, "10-3": 50, "10-4": 30, "15-1": 50, "15-2": 10, "15-3": 50, "15-4": 40, "20-1": 40, "20-2": 20, "20-3": 50, "20-4": 40, "25-1": 100, "25-2": 10, "25-3": 30, "25-4": 10, "30-1": 100, "30-2": 20, "30-3": 10, "30-4": 20}, "Acelerador": {"5-1": false, "5-2": false, "5-3": false, "5-4": false, "10-1": true, "10-2": false, "10-3": true, "10-4": false, "15-1": false, "15-2": false, "15-3": false, "15-4": false, "20-1": false, "20-2": false, "20-3": false, "20-4": false, "25-1": false, "25-2": false, "25-3": true, "25-4": false, "30-1": true, "30-2": false, "30-3": false, "30-4": false}}, "123": {"Dia": {"5-1": 5, "5-2": 5, "5-3": 5, "5-4": 5, "10-1": 10, "10-2": 10, "10-3": 10, "10-4": 10, "15-1": 15, "15-2": 15, "15-3": 15, "15-4": 15, "20-1": 20, "20-2": 20, "20-3": 20, "20-4": 20, "25-1": 25, "25-2": 25, "25-3": 25, "25-4": 25, "30-1": 30, "30-2": 30, "30-3": 30, "30-4": 30}, "Carta": {"5-1": 1, "5-2": 2, "5-3": 3, "5-4": 4, "10-1": 1, "10-2": 2, "10-3": 3, "10-4": 4, "15-1": 1, "15-2": 2, "15-3": 3, "15-4": 4, "20-1": 1, "20-2": 2, "20-3": 3, "20-4": 4, "25-1": 1, "25-2": 2, "25-3": 3, "25-4": 4, "30-1": 1, "30-2": 2, "30-3": 3, "30-4": 4}, "Linha": {"5-1": "Lixas", "5-2": "Mantas NW", "5-3": "Discos de Fibra", "5-4": "Rebolos", "10-1": "Discos Diamantados", "10-2": "Discos de Fibra", "10-3": "Flap Discs", "10-4": "Super Abrasivos", "15-1": "Discos de Corte", "15-2": "Rebolos", "15-3": "Fitas", "15-4": "Super Abrasivos", "20-1": "Lixas", "20-2": "Discos de Fibra", "20-3": "Super Abrasivos", "20-4": "Mantas NW", "25-1": "Discos de Corte", "25-2": "Rebolos", "25-3": "Super Abrasivos", "25-4": "Discos de Fibra", "30-1": "Discos de Corte", "30-2": "Rebolos", "30-3": "Flap Discs", "30-4": "Super Abrasivos"}, "Valor": {"5-1": 100, "5-2": 50, "5-3": 50, "5-4": 50, "10-1": 80, "10-2": 30, "10-3": 10, "10-4": 50, "15-1": 40, "15-2": 10, "15-3": 10, "15-4": 10, "20-1": 50, "20-2": 40, "20-3": 10, "20-4": 10, "25-1": 100, "25-2": 40, "25-3": 30, "25-4": 40, "30-1": 40, "30-2": 20, "30-3": 40, "30-4": 50}, "Acelerador": {"5-1": false, "5-2": false, "5-3": true, "5-4": false, "10-1": false, "10-2": true, "10-3": false, "10-4": false, "15-1": true, "15-2": false, "15-3": false, "15-4": false, "20-1": false, "20-2": true, "20-3": false, "20-4": false, "25-1": true, "25-2": false, "25-3": false, "25-4": true, "30-1": true, "30-2": false, "30-3": false, "30-4": false}}, "159": {"Dia": {"5-1": 5, "5-2": 5, "5-3": 5, "5-4": 5, "10-1": 10, "10-2": 10, "10-3": 10, "10-4": 10, "15-1": 15, "15-2": 15, "15-3": 15, "15-4": 15, "20-1": 20, "20-2": 20, "20-3": 20, "20-4": 20, "25-1": 25, "25-2": 25, "25-3": 25, "25-4": 25, "30-1": 30, "30-2": 30, "30-3": 30, "30-4": 30}, "Carta": {"5-1": 1, "5-2": 2, "5-3": 3, "5-4": 4, "10-1": 1, "10-2": 2, "10-3": 3, "10-4": 4, "15-1": 1, "15-2": 2, "15-3": 3, "15-4": 4, "20-1": 1, "20-2": 2, "20-3": 3, "20-4": 4, "25-1": 1, "25-2": 2, "25-3": 3, "25-4": 4, "30-1": 1, "30-2": 2, "30-3": 3, "30-4": 4}, "Linha": {"5-1": "Discos de Corte", "5-2": "Discos de Fibra", "5-3": "Rebolos", "5-4": "Super Abrasivos", "10-1": "Discos de Corte", "10-2": "Rebolos", "10-3": "Super Abrasivos", "10-4": "Flap Discs", "15-1": "Lixas", "15-2": "Flap Discs", "15-3": "Fitas", "15-4": "Rebolos", "20-1": "Lixas", "20-2": "Super Abrasivos", "20-3": "Fitas", "20-4": "Mantas NW", "25-1": "Discos de Corte", "25-2": "Super Abrasivos", "25-3": "Rebolos", "25-4": "Mantas NW", "30-1": "Discos Diamantados", "30-2": "Fitas", "30-3": "Discos de Fibra", "30-4": "Rebolos"}, "Valor": {"5-1": 100, "5-2": 50, "5-3": 10, "5-4": 10, "10-1": 80, "10-2": 30, "10-3": 30, "10-4": 40, "15-1": 80, "15-2": 30, "15-3": 20, "15-4": 50, "20-1": 80, "20-2": 20, "20-3": 20, "20-4": 30, "25-1": 80, "25-2": 40, "25-3": 40, "25-4": 20, "30-1": 40, "30-2": 20, "30-3": 10, "30-4": 50}, "Acelerador": {"5-1": true, "5-2": true, "5-3": false, "5-4": false, "10-1": true, "10-2": false, "10-3": false, "10-4": false, "15-1": false, "15-2": false, "15-3": false, "15-4": false, "20-1": false, "20-2": false, "20-3": false, "20-4": false, "25-1": true, "25-2": false, "25-3": false, "25-4": false, "30-1": false, "30-2": false, "30-3": true, "30-4": false}}, "190": {"Dia": {"5-1": 5, "5-2": 5, "5-3": 5, "5-4": 5, "10-1": 10, "10-2": 10, "10-3": 10, "10-4": 10, "15-1": 15, "15-2": 15, "15-3": 15, "15-4": 15, "20-1": 20, "20-2": 20, "20-3": 20, "20-4": 20, "25-1": 25, "25-2": 25, "25-3": 25, "25-4": 25, "30-1": 30, "30-2": 30, "30-3": 30, "30-4": 30}, "Carta": {"5-1": 1, "5-2": 2, "5-3": 3, "5-4": 4, "10-1": 1, "10-2": 2, "10-3": 3, "10-4": 4, "15-1": 1, "15-2": 2, "15-3": 3, "15-4": 4, "20-1": 1, "20-2": 2, "20-3": 3, "20-4": 4, "25-1": 1, "25-2": 2, "25-3": 3, "25-4": 4, "30-1": 1, "30-2": 2, "30-3": 3, "30-4": 4}, "Linha": {"5-1": "Discos de Corte", "5-2": "Mantas NW", "5-3": "Discos de Fibra", "5-4": "Rebolos", "10-1": "Discos de Corte", "10-2": "Rebolos", "10-3": "Discos de Fibra", "10-4": "Fitas", "15-1": "Discos de Corte", "15-2": "Super Abrasivos", "15-3": "Discos de Fibra", "15-4": "Mantas NW", "20-1": "Lixas", "20-2": "Mantas NW", "20-3": "Rebolos", "20-4": "Flap Discs", "25-1": "Lixas", "25-2": "Flap Discs", "25-3": "Fitas", "25-4": "Mantas NW", "30-1": "Discos Diamantados", "30-2": "Flap Discs", "30-3": "Discos de Fibra", "30-4": "Super Abrasivos"}, "Valor": {"5-1": 80, "5-2": 30, "5-3": 30, "5-4": 40, "10-1": 80, "10-2": 40, "10-3": 20, "10-4": 40, "15-1": 40, "15-2": 40, "15-3": 10, "15-4": 30, "20-1": 50, "20-2": 10, "20-3": 50, "20-4": 20, "25-1": 100, "25-2": 10, "25-3": 50, "25-4": 50, "30-1": 40, "30-2": 40, "30-3": 40, "30-4": 20}, "Acelerador": {"5-1": true, "5-2": false, "5-3": true, "5-4": false, "10-1": true, "10-2": false, "10-3": true, "10-4": false, "15-1": true, "15-2": false, "15-3": true, "15-4": false, "20-1": false, "20-2": false, "20-3": false, "20-4": false, "25-1": false, "25-2": false, "25-3": false, "25-4": false, "30-1": false, "30-2": false, "30-3": true, "30-4": false}}}}